Ejercicio1/Ejercicio1.v
module FLipFlopD1bit(input wire D,input wire clk,input wire reset, input wire enable,output Q);
reg Q;
	always @(posedge clk or posedge reset)  
		begin
			if(reset)
				begin
					Q <= 0; 
				end
			else if(enable==1) 
				begin
					Q <= D;
				end
			else
				begin
					Q <= Q;
		end
	end
endmodule 

module FLipFlopD2bits(input wire [1:0] D,input wire clk,input wire reset, input wire enable,output [1:0] Q);
FLipFlopD1bit FFD1_1 (D [0], clk, reset, enable, Q [0]);
FLipFlopD1bit FFD1_2 (D [1], clk, reset, enable, Q [1]);
endmodule

module FLipFlopD4bits(input wire [3:0] D,input wire clk,input wire reset, input wire enable,output [3:0] Q);
FLipFlopD2bits FFD2_1 (D [1:0], clk, reset, enable, Q [1:0]);
FLipFlopD2bits FFD2_2 (D [3:2], clk, reset, enable, Q [3:2]);
endmodule

Ejercicio1/Ejercicio1_tb.v
module Ejercicio1_tb();

reg clk, enable, reset; 
reg [3:0]D;
wire [3:0]Q; 

FLipFlopD4bits FFD4b (D, clk, reset, enable, Q);

initial begin
	clk=1;
	forever #5 clk = ~clk;  
end 

initial begin

	#1 $display("");
	$display("Ejercicio 1");
    $display(" D ENABLE | Q ");
    $display("---------|--");
    $monitor(" %d   %d    | %d ", D, enable, Q);
	   
	#2 reset = 1; enable = 0; D = 4'b0000;
	#5 reset = 0;
	
	#10  reset = 0; enable = 0; D = 4'b0000;
	#10  reset = 0; enable = 1; D = 4'b0001;
	#10  reset = 0; enable = 0; D = 4'b0010;
	#10  reset = 0; enable = 1; D = 4'b0011;
	#10  reset = 0; enable = 0; D = 4'b0100;
	#10  reset = 0; enable = 1; D = 4'b0101;
	#10  reset = 0; enable = 0; D = 4'b0110;
	#10  reset = 0; enable = 1; D = 4'b0111;
	#10  reset = 0; enable = 0; D = 4'b1000;
	#10  reset = 0; enable = 1; D = 4'b1001;
	#10  reset = 0; enable = 0; D = 4'b1010;
	#10  reset = 0; enable = 1; D = 4'b1011;
	#10  reset = 0; enable = 0; D = 4'b1100;
	#10  reset = 0; enable = 1; D = 4'b1101;
	#10  reset = 0; enable = 0; D = 4'b1110;
	#10  reset = 0; enable = 1; D = 4'b1111;
	
	
	#10 $display("");
 end
 
initial
#180 $finish; 

initial begin
    $dumpfile("Ejercicio1_tb.vcd");
    $dumpvars(0, Ejercicio1_tb);
end

endmodule

Ejercicio1/Ejercicio1_tb.vcd
$date
	Thu Oct 29 20:05:18 2020
$end
$version
	Icarus Verilog
$end
$timescale
	1ps
$end
$scope module Ejercicio1_tb $end
$var wire 4 ! Q [3:0] $end
$var reg 4 " D [3:0] $end
$var reg 1 # clk $end
$var reg 1 $ enable $end
$var reg 1 % reset $end
$scope module FFD4b $end
$var wire 4 & D [3:0] $end
$var wire 1 # clk $end
$var wire 1 $ enable $end
$var wire 1 % reset $end
$var wire 4 ' Q [3:0] $end
$scope module FFD2_1 $end
$var wire 2 ( D [1:0] $end
$var wire 1 # clk $end
$var wire 1 $ enable $end
$var wire 1 % reset $end
$var wire 2 ) Q [1:0] $end
$scope module FFD1_1 $end
$var wire 1 * D $end
$var wire 1 # clk $end
$var wire 1 $ enable $end
$var wire 1 % reset $end
$var reg 1 + Q $end
$upscope $end
$scope module FFD1_2 $end
$var wire 1 , D $end
$var wire 1 # clk $end
$var wire 1 $ enable $end
$var wire 1 % reset $end
$var reg 1 - Q $end
$upscope $end
$upscope $end
$scope module FFD2_2 $end
$var wire 2 . D [1:0] $end
$var wire 1 # clk $end
$var wire 1 $ enable $end
$var wire 1 % reset $end
$var wire 2 / Q [1:0] $end
$scope module FFD1_1 $end
$var wire 1 0 D $end
$var wire 1 # clk $end
$var wire 1 $ enable $end
$var wire 1 % reset $end
$var reg 1 1 Q $end
$upscope $end
$scope module FFD1_2 $end
$var wire 1 2 D $end
$var wire 1 # clk $end
$var wire 1 $ enable $end
$var wire 1 % reset $end
$var reg 1 3 Q $end
$upscope $end
$upscope $end
$upscope $end
$upscope $end
$enddefinitions $end
#0
$dumpvars
x3
x2
x1
x0
bx /
bx .
x-
x,
x+
x*
bx )
bx (
bx '
bx &
x%
x$
1#
bx "
bx !
$end
#3
03
b0 /
01
0-
b0 !
b0 '
b0 )
0+
0*
0,
00
02
b0 (
b0 .
b0 "
b0 &
0$
1%
#5
0#
#8
0%
#10
1#
#15
0#
#20
1#
#25
0#
#28
1*
b1 (
b1 "
b1 &
1$
#30
b1 !
b1 '
b1 )
1+
1#
#35
0#
#38
0*
1,
b10 (
b10 "
b10 &
0$
#40
1#
#45
0#
#48
1*
b11 (
b11 "
b11 &
1$
#50
b11 !
b11 '
b11 )
1-
1#
#55
0#
#58
0*
0,
10
b0 (
b1 .
b100 "
b100 &
0$
#60
1#
#65
0#
#68
1*
b1 (
b101 "
b101 &
1$
#70
b1 )
0-
b101 !
b101 '
b1 /
11
1#
#75
0#
#78
0*
1,
b10 (
b110 "
b110 &
0$
#80
1#
#85
0#
#88
1*
b11 (
b111 "
b111 &
1$
#90
b111 !
b111 '
b11 )
1-
1#
#95
0#
#98
0*
0,
00
12
b0 (
b10 .
b1000 "
b1000 &
0$
#100
1#
#105
0#
#108
1*
b1 (
b1001 "
b1001 &
1$
#110
b1 )
0-
01
b1001 !
b1001 '
b10 /
13
1#
#115
0#
#118
0*
1,
b10 (
b1010 "
b1010 &
0$
#120
1#
#125
0#
#128
1*
b11 (
b1011 "
b1011 &
1$
#130
b1011 !
b1011 '
b11 )
1-
1#
#135
0#
#138
0*
0,
10
b0 (
b11 .
b1100 "
b1100 &
0$
#140
1#
#145
0#
#148
1*
b1 (
b1101 "
b1101 &
1$
#150
b1 )
0-
b1101 !
b1101 '
b11 /
11
1#
#155
0#
#158
0*
1,
b10 (
b1110 "
b1110 &
0$
#160
1#
#165
0#
#168
1*
b11 (
b1111 "
b1111 &
1$
#170
b1111 !
b1111 '
b11 )
1-
1#
