Ejercicio3/Ejercicio3.v
module FLipFlopD1bit(input wire D,input wire clk,input wire reset, input wire enable,output Q);
reg Q;
	always @(posedge clk or posedge reset)  
		begin
			if(reset)
				begin
					Q <= 0; 
				end
			else if(enable==1) 
				begin
					Q <= D;
				end
			else
				begin
					Q <= Q;
		end
	end
endmodule 

module FlipFlopJK (input wire J, input wire K, input wire clk,input wire reset, input wire enable,output Q);
wire D;
	assign D = (~Q & J)|(Q & ~K);
	FLipFlopD1bit FFD_1 (D, clk, reset, enable, Q);
endmodule

Ejercicio3/Ejercicio3_tb.v
module Ejercicio3_tb();

reg clk, enable, reset; 
reg J; reg K; wire Q; 

FlipFlopJK FFJK_1 (J, K , clk, reset, enable, Q);

initial begin
	clk=1;
	forever #5 clk = ~clk;  
end 

initial begin
	#1 $display("");
	$display("Ejercicio 3");
    $display(" J K ENABLE | Q ");
    $display("------------|--");
    $monitor(" %d %d    %d   | %d ", J, K, enable, Q);
	#2 reset = 1; enable = 0; J = 0; K = 0;
	#5 reset = 0;
	#10  reset = 0; enable = 1; J = 0; K = 0;
	#10  reset = 0; enable = 1; J = 0; K = 0;
	#10  reset = 0; enable = 1; J = 1; K = 0;
	#10  reset = 0; enable = 1; J = 1; K = 0;
	#10  reset = 0; enable = 1; J = 0; K = 1;
	#10  reset = 0; enable = 1; J = 0; K = 1;
	#10  reset = 0; enable = 1; J = 1; K = 1;
	#10  reset = 0; enable = 1; J = 1; K = 1;
	
	#10 $display("");
 end 
initial
#100 $finish; 
initial begin
    $dumpfile("Ejercicio3_tb.vcd");
    $dumpvars(0, Ejercicio3_tb);
end

endmodule

Ejercicio3/Ejercicio3_tb.vcd
$date
	Thu Oct 29 23:31:41 2020
$end
$version
	Icarus Verilog
$end
$timescale
	1ps
$end
$scope module Ejercicio3_tb $end
$var wire 1 ! Q $end
$var reg 1 " J $end
$var reg 1 # K $end
$var reg 1 $ clk $end
$var reg 1 % enable $end
$var reg 1 & reset $end
$scope module FFJK_1 $end
$var wire 1 ' D $end
$var wire 1 " J $end
$var wire 1 # K $end
$var wire 1 $ clk $end
$var wire 1 % enable $end
$var wire 1 & reset $end
$var wire 1 ! Q $end
$scope module FFD_1 $end
$var wire 1 ' D $end
$var wire 1 $ clk $end
$var wire 1 % enable $end
$var wire 1 & reset $end
$var reg 1 ! Q $end
$upscope $end
$upscope $end
$upscope $end
$enddefinitions $end
#0
$dumpvars
x'
x&
x%
1$
x#
x"
x!
$end
#3
0'
0!
0#
0"
0%
1&
#5
0$
#8
0&
#10
1$
#15
0$
#18
1%
#20
1$
#25
0$
#30
1$
#35
0$
#38
1'
1"
#40
1!
1$
#45
0$
#50
1$
#55
0$
#58
0'
1#
0"
#60
0!
1$
#65
0$
#70
1$
#75
0$
#78
1'
1"
#80
0'
1!
1$
#85
0$
#90
1'
0!
1$
#95
0$
#100
0'
1!
1$
